geoip.py
python_geoip-1.1.dist-info/DESCRIPTION.rst
python_geoip-1.1.dist-info/METADATA
python_geoip-1.1.dist-info/pydist.json
python_geoip-1.1.dist-info/RECORD
python_geoip-1.1.dist-info/top_level.txt
python_geoip-1.1.dist-info/WHEEL
