Metadata-Version: 2.0
Name: python-geoip
Version: 1.1
Summary: Provides GeoIP functionality for Python.
Home-page: http://github.com/mitsuhiko/python-geoip
Author: Armin Ronacher
Author-email: armin.ronacher@active-4.com
License: UNKNOWN
Platform: UNKNOWN
Classifier: Programming Language :: Python
Classifier: License :: OSI Approved :: BSD License
